AUTHORS
LICENSE
MANIFEST.in
README.rst
requirements.txt
setup.py
version.py
alignak_demo/__init__.py
alignak_demo.egg-info/PKG-INFO
alignak_demo.egg-info/SOURCES.txt
alignak_demo.egg-info/dependency_links.txt
alignak_demo.egg-info/not-zip-safe
alignak_demo.egg-info/requires.txt
alignak_demo.egg-info/top_level.txt
alignak_demo/etc/alignak-backend-import.cfg
alignak_demo/etc/alignak.cfg
alignak_demo/etc/alignak.ini
alignak_demo/etc/arbiter/daemons/arbiter-master.cfg
alignak_demo/etc/arbiter/daemons/broker-master.cfg
alignak_demo/etc/arbiter/daemons/poller-master.cfg
alignak_demo/etc/arbiter/daemons/reactionner-master.cfg
alignak_demo/etc/arbiter/daemons/receiver-master.cfg
alignak_demo/etc/arbiter/daemons/scheduler-master.cfg
alignak_demo/etc/arbiter/daemons/North/broker-north.cfg
alignak_demo/etc/arbiter/daemons/North/poller-north.cfg
alignak_demo/etc/arbiter/daemons/North/receiver-north.cfg
alignak_demo/etc/arbiter/daemons/North/scheduler-north.cfg
alignak_demo/etc/arbiter/daemons/South/broker-south.cfg
alignak_demo/etc/arbiter/daemons/South/poller-south.cfg
alignak_demo/etc/arbiter/daemons/South/scheduler-south.cfg
alignak_demo/etc/arbiter/daemons/South/South-East/broker-south-east.cfg
alignak_demo/etc/arbiter/daemons/South/South-East/poller-south-east.cfg
alignak_demo/etc/arbiter/daemons/South/South-East/scheduler-south-east.cfg
alignak_demo/etc/arbiter/modules/mod-alignak_backend_arbiter.cfg
alignak_demo/etc/arbiter/modules/mod-alignak_backend_broker.cfg
alignak_demo/etc/arbiter/modules/mod-alignak_backend_scheduler.cfg
alignak_demo/etc/arbiter/modules/mod-external-commands.cfg
alignak_demo/etc/arbiter/modules/mod-logs-logger.json
alignak_demo/etc/arbiter/modules/mod-logs.cfg
alignak_demo/etc/arbiter/modules/mod-nrpe-booster.cfg
alignak_demo/etc/arbiter/modules/mod-nsca-north.cfg
alignak_demo/etc/arbiter/modules/mod-nsca.cfg
alignak_demo/etc/arbiter/modules/mod-ws.cfg
alignak_demo/etc/arbiter/modules/readme.cfg
alignak_demo/etc/arbiter/objects/commands/detailled-host-by-email.cfg
alignak_demo/etc/arbiter/objects/commands/detailled-service-by-email.cfg
alignak_demo/etc/arbiter/objects/commands/notify-host-by-email.cfg
